nistrng/__init__.py
nistrng/functions.py
nistrng/test.py
nistrng/sp800_22r1a/__init__.py
nistrng/sp800_22r1a/test_approximate_entropy.py
nistrng/sp800_22r1a/test_binary_matrix_rank.py
nistrng/sp800_22r1a/test_cumulative_sums.py
nistrng/sp800_22r1a/test_discrete_fourier_transform.py
nistrng/sp800_22r1a/test_frequency_within_block.py
nistrng/sp800_22r1a/test_linear_complexity.py
nistrng/sp800_22r1a/test_longest_run_ones_in_a_block.py
nistrng/sp800_22r1a/test_maurers_universal.py
nistrng/sp800_22r1a/test_monobit.py
nistrng/sp800_22r1a/test_non_overlapping_template_matching.py
nistrng/sp800_22r1a/test_overlapping_template_matching.py
nistrng/sp800_22r1a/test_random_excursion.py
nistrng/sp800_22r1a/test_random_excursion_variant.py
nistrng/sp800_22r1a/test_runs.py
nistrng/sp800_22r1a/test_serial.py
nistrngg987/__init__.py
nistrngg987/functions.py
nistrngg987/test.py
nistrngg987/sp800_22r1a/__init__.py
nistrngg987/sp800_22r1a/test_approximate_entropy.py
nistrngg987/sp800_22r1a/test_binary_matrix_rank.py
nistrngg987/sp800_22r1a/test_cumulative_sums.py
nistrngg987/sp800_22r1a/test_discrete_fourier_transform.py
nistrngg987/sp800_22r1a/test_frequency_within_block.py
nistrngg987/sp800_22r1a/test_linear_complexity.py
nistrngg987/sp800_22r1a/test_longest_run_ones_in_a_block.py
nistrngg987/sp800_22r1a/test_maurers_universal.py
nistrngg987/sp800_22r1a/test_monobit.py
nistrngg987/sp800_22r1a/test_non_overlapping_template_matching.py
nistrngg987/sp800_22r1a/test_overlapping_template_matching.py
nistrngg987/sp800_22r1a/test_random_excursion.py
nistrngg987/sp800_22r1a/test_random_excursion_variant.py
nistrngg987/sp800_22r1a/test_runs.py
nistrngg987/sp800_22r1a/test_serial.py
nistrngg987-1.2.3.dist-info/LICENSE.txt
nistrngg987-1.2.3.dist-info/METADATA
nistrngg987-1.2.3.dist-info/WHEEL
nistrngg987-1.2.3.dist-info/top_level.txt
nistrngg987-1.2.3.dist-info/RECORD
