Metadata-Version: 2.1
Name: nistrngg987
Version: 1.2.3
Summary: NIST Test Suite for Random Number Generators - SAILab - University of Siena
Home-page: https://github.com/InsaneMonster/NistRng
Author: Luca Pasqualini
Author-email: pasqualini@diism.unisi.it
License: BSD 3-Clause
Keywords: NIST Tests RNG Random Number Generator SAILab USiena Siena SP800-22r1a
Classifier: Development Status :: 5 - Production/Stable
Classifier: License :: OSI Approved :: BSD License
Classifier: Programming Language :: Python :: 3.6
Classifier: Topic :: Security :: Cryptography
License-File: LICENSE.txt
Requires-Dist: numpy >=1.14.5
Requires-Dist: scipy >=1.2.2
